Metadata-Version: 1.0
Name: distributions-BinomialGauss
Version: 0.26
Summary: Gaussian and Binomial distributions
Home-page: UNKNOWN
Author: Bruno Prado
Author-email: brunoibmec@gmail.com
License: UNKNOWN
Platform: UNKNOWN
